datakit_gitlab/__init__.py
datakit_gitlab/git.py
datakit_gitlab/gitlab_project.py
datakit_gitlab/project_mixin.py
datakit_gitlab/commands/__init__.py
datakit_gitlab/commands/integrate.py
datakit_gitlab/commands/issues/__init__.py
datakit_gitlab/commands/issues/add.py
tests/__init__.py
tests/conftest.py
tests/commands/__init__.py
tests/commands/test_integrate.py
tests/commands/test_issues_add.py
tests/fixtures/current_user_get.json
tests/fixtures/group_id_lookup.json
tests/fixtures/issue_added_201.json
tests/fixtures/project_created-201.json
tests/fixtures/project_get.json
tests/fixtures/project_search-already_exists.json
datakit_gitlab-0.6.0.dist-info/LICENSE
datakit_gitlab-0.6.0.dist-info/METADATA
datakit_gitlab-0.6.0.dist-info/WHEEL
datakit_gitlab-0.6.0.dist-info/entry_points.txt
datakit_gitlab-0.6.0.dist-info/top_level.txt
datakit_gitlab-0.6.0.dist-info/RECORD
