Metadata-Version: 2.1
Name: datakit-gitlab
Version: 0.6.0
Summary: Commands to manage project integration with Gitlab.
Home-page: https://github.com/associatedpress/datakit-gitlab
Author: Serdar Tumgoren
Author-email: stumgoren@ap.org
License: ISC license
Keywords: datakit-gitlab
Classifier: Development Status :: 2 - Pre-Alpha
Classifier: Environment :: Console
Classifier: Intended Audience :: Developers
Classifier: License :: OSI Approved :: ISC License (ISCL)
Classifier: Natural Language :: English
Classifier: Programming Language :: Python :: 3
Classifier: Programming Language :: Python :: 3.3
Classifier: Programming Language :: Python :: 3.4
Classifier: Programming Language :: Python :: 3.5
Classifier: Programming Language :: Python :: 3.6
License-File: LICENSE
Requires-Dist: cliff
Requires-Dist: datakit-core
Requires-Dist: python-gitlab >=2.5.0
